gdtransform/__init__.py
gdtransform/constants.py
gdtransform/introspect.py
gdtransform/test.py
gdtransform/transform.py
gdtransform-0.1.2.dist-info/LICENSE
gdtransform-0.1.2.dist-info/METADATA
gdtransform-0.1.2.dist-info/WHEEL
gdtransform-0.1.2.dist-info/top_level.txt
gdtransform-0.1.2.dist-info/RECORD
